LICENSE
MANIFEST.in
README.md
pycnc
setup.cfg
setup.py
cnc/__init__.py
cnc/config.py
cnc/coordinates.py
cnc/enums.py
cnc/gcode.py
cnc/gmachine.py
cnc/hal.py
cnc/hal_virtual.py
cnc/heater.py
cnc/logging_config.py
cnc/main.py
cnc/pid.py
cnc/pulses.py
cnc/hal_raspberry/__init__.py
cnc/hal_raspberry/hal.py
cnc/hal_raspberry/rpgpio.py
cnc/hal_raspberry/rpgpio_private.py
cnc/sensors/__init__.py
cnc/sensors/ads111x.py
cnc/sensors/thermistor.py
pycnc.egg-info/PKG-INFO
pycnc.egg-info/SOURCES.txt
pycnc.egg-info/dependency_links.txt
pycnc.egg-info/top_level.txt
tests/__init__.py
tests/test_coordinates.py
tests/test_gcode.py
tests/test_gmachine.py
tests/test_heater.py
tests/test_pid.py
tests/test_pulses.py