Metadata-Version: 1.0
Name: pycnc
Version: 1.0.0
Summary: CNC machine controller
Home-page: https://github.com/Nikolay-Kha/PyCNC
Author: Nikolay Khabarov
Author-email: 2xl@mail.ru
License: MIT
Keywords: CNC 3D printer robot raspberry pi
Platform: UNKNOWN
